stats_can_ext/__init__.py
stats_can_ext/helpers.py
stats_can_ext/sc.py
stats_can_ext/scwds.py
stats_can_ext/stats_can.py
stats_can_ext-0.0.2.dist-info/WHEEL
stats_can_ext-0.0.2.dist-info/METADATA
stats_can_ext-0.0.2.dist-info/RECORD
