Metadata-Version: 2.4
Name: stats-can-ext
Version: 0.0.2
Summary: Interface ontop of StatsCan
Keywords: statistics,Canada,data,API
Author: Eric Schles
License-Expression: GPL-3.0-or-later
Requires-Dist: requests
Requires-Dist: tqdm
Requires-Dist: pandas
Requires-Dist: numpy
Requires-Python: >=3.10, <4.0
Project-URL: Documentation, https://stats-can.readthedocs.io
Project-URL: Homepage, https://github.com/EricSchles/stats_can-ext
Project-URL: Repository, https://github.com/EricSchles/stats_can-ext
